orbslam3.so
orbslam3-0.0.dist-info/METADATA
orbslam3-0.0.dist-info/WHEEL
orbslam3-0.0.dist-info/top_level.txt
orbslam3-0.0.dist-info/zip-safe
orbslam3-0.0.dist-info/RECORD
